[
    {
        "message": "标签 'meta' 中的属性 'content' 的属性 'width' 被设置为 'device-width.minimum-scale'，该属性值无效",
        "code": "06200401",
        "line": 5,
        "col": 9,
        "offset": 77,
        "input": "        <meta name=\"viewport\" content=\"width=device-width.minimum-scale=1.initial-scale=1\">"
    },
    {
        "message": "标签 'meta' 中的属性 'content' 的属性 'initial-scale' 被设置为 ''，该属性值无效",
        "code": "06200401",
        "line": 5,
        "col": 9,
        "offset": 77,
        "input": "        <meta name=\"viewport\" content=\"width=device-width.minimum-scale=1.initial-scale=1\">"
    }
]
